segmenteverygrain/__init__.py
segmenteverygrain/grain_utils.py
segmenteverygrain/interactions.py
segmenteverygrain/segmenteverygrain.py
segmenteverygrain-0.2.5.dist-info/licenses/LICENSE.txt
segmenteverygrain-0.2.5.dist-info/METADATA
segmenteverygrain-0.2.5.dist-info/WHEEL
segmenteverygrain-0.2.5.dist-info/top_level.txt
segmenteverygrain-0.2.5.dist-info/RECORD
